falconpytools/__init__.py
falconpytools/_api.py
falconpytools/_tool.py
falconpytools/_toolbox.py
falconpytools/_version.py
falconpytools/hosts/__init__.py
falconpytools/hosts/_api.py
falconpytools/hosts/_host.py
falconpytools/rtr/__init__.py
falconpytools/rtr/_api.py
falconpytools/rtr/_files.py
falconpytools/rtr/_scripts.py
falconpytools/rtr/_single_target.py
crowdstrike_falconpy_tools-0.0.28.dist-info/LICENSE
crowdstrike_falconpy_tools-0.0.28.dist-info/METADATA
crowdstrike_falconpy_tools-0.0.28.dist-info/WHEEL
crowdstrike_falconpy_tools-0.0.28.dist-info/top_level.txt
crowdstrike_falconpy_tools-0.0.28.dist-info/RECORD
