Metadata-Version: 2.1
Name: crowdstrike-falconpy-tools
Version: 0.0.28
Summary: CrowdStrike FalconPy Tools
Home-page: https://github.com/CrowdStrike/falconpy-tools
Author: CrowdStrike
Author-email: falconpy@crowdstrike.com
Maintainer: Joshua Hiller
Maintainer-email: falconpy@crowdstrike.com
License: UNKNOWN
Project-URL: Source, https://github.com/CrowdStrike/falconpy-tools/tree/main/src/falconpytools
Project-URL: Tracker, https://github.com/CrowdStrike/falconpy-tools/issues
Keywords: crowdstrike,falcon,api,sdk,oauth2,devsecops,tools
Platform: UNKNOWN
Classifier: Development Status :: 4 - Beta
Classifier: Intended Audience :: Developers
Classifier: Operating System :: Unix
Classifier: Operating System :: POSIX
Classifier: Operating System :: MacOS
Classifier: Operating System :: Microsoft :: Windows
Classifier: Operating System :: OS Independent
Classifier: Programming Language :: Python :: 3
Classifier: Programming Language :: Python :: 3.6
Classifier: Programming Language :: Python :: 3.7
Classifier: Programming Language :: Python :: 3.8
Classifier: Programming Language :: Python :: 3.9
Classifier: License :: OSI Approved :: The Unlicense (Unlicense)
Classifier: Topic :: Software Development :: Libraries :: Python Modules
Classifier: Topic :: System :: Systems Administration
Classifier: Topic :: Utilities
Requires-Python: >=3.6
Requires-Dist: crowdstrike-falconpy
Provides-Extra: dev
Requires-Dist: flake8 ; extra == 'dev'
Requires-Dist: coverage ; extra == 'dev'
Requires-Dist: pylint ; extra == 'dev'
Requires-Dist: pytest-cov ; extra == 'dev'
Requires-Dist: pytest ; extra == 'dev'
Requires-Dist: bandit ; extra == 'dev'
